mande_integration_gisel/__init__.py
mande_integration_gisel/command.py
mande_integration_gisel/config/__init__.py
mande_integration_gisel/config/selectors.py
mande_integration_gisel/config/types.py
mande_integration_gisel/config/variables.py
mande_integration_gisel/main.py
mande_integration_gisel/organizations.py
mande_integration_gisel/utils/__init__.py
mande_integration_gisel-1.0.8.dist-info/METADATA
mande_integration_gisel-1.0.8.dist-info/WHEEL
mande_integration_gisel-1.0.8.dist-info/entry_points.txt
mande_integration_gisel-1.0.8.dist-info/RECORD
